mizani/__init__.py
mizani/bounds.py
mizani/breaks.py
mizani/formatters.py
mizani/labels.py
mizani/palettes.py
mizani/py.typed
mizani/scale.py
mizani/transforms.py
mizani/typing.py
mizani/utils.py
mizani/_colors/__init__.py
mizani/_colors/_named_color_values.py
mizani/_colors/hsluv.py
mizani/_colors/named_colors.py
mizani/_colors/utils.py
mizani/_colors/_colormaps/__init__.py
mizani/_colors/_colormaps/_colormap.py
mizani/_colors/_colormaps/_cubehelix.py
mizani/_colors/_colormaps/_interpolated.py
mizani/_colors/_colormaps/_listed.py
mizani/_colors/_colormaps/_palette_interpolated.py
mizani/_colors/_colormaps/_segment_function.py
mizani/_colors/_colormaps/_segment_interpolated.py
mizani/_colors/_colormaps/_maps/__init__.py
mizani/_colors/_colormaps/_maps/_interpolated.py
mizani/_colors/_colormaps/_maps/_listed.py
mizani/_colors/_colormaps/_maps/_palette_interpolated.py
mizani/_colors/_colormaps/_maps/_segment_function.py
mizani/_colors/_colormaps/_maps/_segment_interpolated.py
mizani/_colors/_palettes/__init__.py
mizani/_colors/_palettes/_palette.py
mizani/_colors/_palettes/brewer/__init__.py
mizani/_colors/_palettes/brewer/diverging.py
mizani/_colors/_palettes/brewer/qualitative.py
mizani/_colors/_palettes/brewer/sequential.py
mizani/_colors/_palettes/other/__init__.py
mizani/_colors/_palettes/other/qualitative.py
mizani/_datetime/__init__.py
mizani/_datetime/breaks.py
mizani/_datetime/rounding.py
mizani/_datetime/types.py
mizani/_datetime/utils.py
mizani/_timedelta/__init__.py
mizani/_timedelta/breaks.py
mizani/_timedelta/utils.py
mizani-0.14.1.dist-info/licenses/LICENSE
mizani-0.14.1.dist-info/METADATA
mizani-0.14.1.dist-info/WHEEL
mizani-0.14.1.dist-info/top_level.txt
mizani-0.14.1.dist-info/RECORD
