Metadata-Version: 2.4
Name: mizani
Version: 0.14.1
Summary: Scales for Python
Author-email: Hassan Kibirige <has2k1@gmail.com>
License: Copyright (c) 2016, Hassan Kibirige
Project-URL: homepage, https://mizani.readthedocs.io/en/stable
Project-URL: repository, https://github.com/has2k1/mizani
Project-URL: changelog, https://mizani.readthedocs.io/en/stable/changelog.html
Project-URL: ci, https://github.com/has2k1/mizani/actions
Classifier: Intended Audience :: Science/Research
Classifier: License :: OSI Approved :: BSD License
Classifier: Programming Language :: Python :: 3 :: Only
Classifier: Programming Language :: Python :: 3.10
Classifier: Programming Language :: Python :: 3.11
Classifier: Programming Language :: Python :: 3.12
Classifier: Programming Language :: Python :: 3.13
Classifier: Topic :: Scientific/Engineering :: Visualization
Requires-Python: >=3.10
License-File: LICENSE
Requires-Dist: numpy>=1.23.5
Requires-Dist: scipy>=1.8.0
Requires-Dist: pandas>=2.2.0
Requires-Dist: tzdata; platform_system == "Windows" or platform_system == "Emscripten"
Provides-Extra: all
Requires-Dist: mizani[doc]; extra == "all"
Requires-Dist: mizani[build]; extra == "all"
Requires-Dist: mizani[lint]; extra == "all"
Requires-Dist: mizani[test]; extra == "all"
Requires-Dist: mizani[dev]; extra == "all"
Provides-Extra: doc
Requires-Dist: sphinx>=7.2.0; extra == "doc"
Requires-Dist: numpydoc>=1.7.0; extra == "doc"
Provides-Extra: rtd
Requires-Dist: mock; extra == "rtd"
Provides-Extra: build
Requires-Dist: build; extra == "build"
Requires-Dist: wheel; extra == "build"
Provides-Extra: lint
Requires-Dist: ruff; extra == "lint"
Provides-Extra: test
Requires-Dist: pytest-cov>=4.0.0; extra == "test"
Provides-Extra: dev
Requires-Dist: notebook; extra == "dev"
Requires-Dist: twine; extra == "dev"
Requires-Dist: pre-commit; extra == "dev"
Requires-Dist: mizani[typing]; extra == "dev"
Provides-Extra: typing
Requires-Dist: pyright==1.1.402; extra == "typing"
Requires-Dist: pandas-stubs; extra == "typing"
Dynamic: license-file
